{
  "403033": "FROM.FRAIS 1/2 SEL 25 G X24",
  "432241": "OEUF BROUILLE NAT P. AIR 500 G",
  "302616": "GRAINE COURGE 500G *BIO",
  "222949": "PATE A TARTINER NOIS.400G",
  "232456": "BLANC DINDE 40G X10",
  "241966": "CANTAL JEUNE TR.28% 30GX24 AOP",
  "209312": "YAOURT PECHE/ABRICOT PC 125GX8",
  "311569": "EMMENTAL FR.TR.BURGER 29% 340G",
  "317397": "INFUSION TILLEUL MENT. X25*BIO",
  "257545": "GRANOLA NAT.S/GLUTEN 500G *BIO",
  "301231": "SALADE 4 FRUITS 3L",
  "252351": "BRIOCHE TRANCHEE 500G AGRI",
  "252941": "MUESLI GRANOLA CAN/GOJI 500GX7",
  "302123": "POM.GOLD.136/165 FR.2KG",
  "494294": "BEURRE MICROPAIN 1/2S.10G X100",
  "237731": "CANDEREL SUCRALOSE BUCHET.X250",
  "476044": "PETIT MOULE NAT 21% 16.67 GX24",
  "204134": "YAOURT NATURE 125 G X4 *BIO",
  "494302": "BEURRE MICROPAIN DOUX 10G X100",
  "302242": "MINI CREPE SUCREE 15G X120*BIO",
  "301714": "BEURRE 1/2 SEL 250 G *BIO",
  "242686": "OEUF FRAIS VRAC MOYEN P.AIRX90",
  "429368": "RADIS ROSE X 2 BOTTES VD VQ",
  "277504": "KETCHUP MINI SQUEEZ 280G",
  "503019": "BACON CRISPY LAMELLE 500 G VPF",
  "70075": "PREPA.PECHE DE VIGNE 320G",
  "245099": "BACON CRISPY TRANCHE 500 G",
  "209315": "YAOURT FRAISE/FRAMB.PC 125G X8",
  "209374": "MADELEINE S/GLUTEN 30G X45",
  "216965": "FROM.FRAIS FRUITS 0% 100GX4 X6",
  "507687": "THE EARL GREY X20 *BIO",
  "302524": "LAIT 1/2 ECREME BRICK UHT 1 L",
  "404655": "PAIN CHOCO.PAC 70G X114",
  "234616": "PAVE NORDIQUE 280G X28 *BIO",
  "404647": "PAVE MUESLI PREC.LALOS 280GX26",
  "404682": "CROISSANT PAC 60G X76",
  "200668": "BAGUETTE ESSEN./SOLE 280G X25",
  "245202": "EMINCE FLT PLT ROTI 1KG HALAL",
  "300744": "EMINCE FLT PLT ROTI IQF 1KG",
  "483784": "PARMIGIANO PETALE 500 G AOP",
  "101744": "PAIN POCHON LALOS 450 G X16",
  "505064": "MOELLEUX CHOCO.S/GLUTEN 27G",
  "244290": "TORTILLA PDT/OIGNON 130 G X40",
  "868475": "ORANGE NAVELATE 7/8 10KG *BIO",
  "208328": "ST NECTAIRE TR.27% 30G X24 AOP",
  "215501": "MINI CROISSANT PREP.30G X200",
  "215502": "MINI PAIN RAISIN PREP.30G X192",
  "204344": "ROSETTE TR.5GX50 250G LR",
  "310022": "BATAVIA FEUILLE 1 KG",
  "422740": "BANANE P20 5KG VQ",
  "302244": "BOISSON AVOINE 1 L *BIO",
  "447466": "GAUFRE MIN.SWEET TIME 15GX50",
  "838956": "EAU MINERALE O9  B&B 50CL",
  "301230": "SALADE 6 FRUITS 3 L",
  "213569": "TISANE DETENTE BTE X20 *BIO",
  "302146": "PAVE BREBIS 1 KG *BIO",
  "215388": "PAIN CAMPAGNE 400G X15 *BIO",
  "205590": "PRUNEAU DENOYAUTE 60/70 1KG",
  "980987": "NUTELLA 750G",
  "208865": "CONF.FRAISE 320G",
  "212961": "CONF.4 AGRUMES 320G",
  "971052": "POM.R.GALA 170/200 FR.4KG VQ",
  "246113": "CRACOTTE FROMENT 36TR. 250G",
  "450635": "INFUSION TILLEUL MENTHE X25",
  "218166": "OEUF FRAIS MOYEN CAT3 X60",
  "249597": "FROM.FRAIS NATURE 0% 100 G X4",
  "301573": "OEUF FRAIS MOYEN P.AIR X12 LR",
  "302492": "GRAINE DE CHIA 500G",
  "245379": "CAFE SOLUBLE DECA.ARABICA X100",
  "301398": "ROSETTE TR.10GX50 500G",
  "213581": "THE VERT MENTHE X20 *BIO",
  "252641": "ASSORT.4COMPOTE ALL.CP100GX120",
  "241963": "ALPRO AMANDE A BOIRE 1 L",
  "485409": "LAIT ENTIER 9.7ML X240",
  "961566": "SEL ADOUCISSEUR EAU 10 KG",
  "238905": "OEUF FRAIS MOYEN CAT3 X30",
  "524174": "POMME JONAGOLD 135/170 FR 2KG",
  "967385": "POM.BICOLORE 136/165 FR.2KG",
  "208866": "CONF.ABRICOT 320G",
  "302558": "BISCOTTE FROMENT 90TR.675 G",
  "142778": "BEURRE MICROPAIN 1/2S.10GX100",
  "300616": "CROISS.PAC BEUR. 70G X60",
  "217425": "PAIN S/GLUTEN IND.45 G X50",
  "487067": "KIWI CAL39 *BIO VQ",
  "217176": "PAIN FIGUE LALOS 330 G X26",
  "208879": "EDULCORANT COMPRIME IND.X500",
  "450192": "CREME CARAMEL SEL GUER. 360G",
  "243706": "SAUCISSE DEJ PETIT VOL.25GX40",
  "301491": "SUCRE BUCHETTE 4 G X750",
  "302615": "GRAINE DE LIN 1KG *BIO",
  "257752": "LAIT 1/2 ECREME UHT BRICK 1 L",
  "272625": "PAVE MULTICERE.PREC.450 G X30",
  "317400": "THE NOIR CEYLAN X25 *BIO",
  "217157": "YAOURT AROM. VANILLE 125GX24",
  "583568": "MIEL CREMEUX PV 375 G",
  "999078": "FRAIS TRANSPORT",
  "255588": "OEUF BROUILLE NATURE 500 G",
  "302259": "CRANBERRIES 500G *BIO",
  "222457": "FROM.FRAIS LIT FRT 7% 100GX24",
  "317402": "THE NOIR CHAI X25",
  "641118": "THE EARL GREY SF X25",
  "244190": "SAUCISSE PETIT DEJ PREC 25GX40",
  "430311": "BRASSE VEGETA.LAIT COCO 400 G",
  "623703": "KNAX VEGETAL 50G 3 KG",
  "966271": "ESTRAGON BOTTE 30G",
  "317398": "INFUSION VERVEINE X25 *BIO",
  "495176": "LAIT 1/2 ECREME UHT BRICK 1 L",
  "302495": "BEURRE DEMI SEL 250G",
  "218989": "JAMBON CUIT SUP.DD.40GX20 VPF",
  "317341": "CORN FLAKES NATURE 750GR",
  "300093": "POITRINE FUME TR.FINE 400G VPF",
  "864976": "ORANGE LANE LATE 7/8 2KG",
  "215675": "JAMBON PARIS SPEC.SDW 40GX20TR",
  "208709": "CAMEMBERT LAIT PAST.21% 240G",
  "533889": "POM.GOLD 201/240 FR.4KG VQ",
  "252682": "THE EARL GREY EXCELLEN.X25*BIO",
  "900311": "COMP.POMME ALL.CP 100 G X120",
  "249811": "FROM.BLANC FRUIT 2.4% 100 G X4",
  "240572": "BLANC POULET 40G X10",
  "302613": "CAMEMBERT LT PASTEUR.250G *BIO",
  "215768": "BAIE GOJI SECHEE 1KG",
  "59840": "NESCAFE SELECT.DECA 2G X300",
  "394810": "BANANE P20 MAIN 5F.800G"
}